{"Query":{"fields":{"continents":{"type":"Continent","args":{"filter":["ContinentFilterInput","ContinentFilterInput"]}},"continent":{"type":"Continent","args":{"code":["ID!","ID"]}},"countries":{"type":"Country","args":{"filter":["CountryFilterInput","CountryFilterInput"]}},"country":{"type":"Country","args":{"code":["ID!","ID"]}},"languages":{"type":"Language","args":{"filter":["LanguageFilterInput","LanguageFilterInput"]}},"language":{"type":"Language","args":{"code":["ID!","ID"]}},"__typename":{"type":"String"}}},"ContinentFilterInput":{"fields":{"code":{"type":"StringQueryOperatorInput"},"__typename":{"type":"String"}}},"StringQueryOperatorInput":{"fields":{"eq":{"type":"String"},"ne":{"type":"String"},"in":{"type":"String"},"nin":{"type":"String"},"regex":{"type":"String"},"glob":{"type":"String"},"__typename":{"type":"String"}}},"String":{"__isAUsedScalarType":true},"Continent":{"fields":{"code":{"type":"ID"},"name":{"type":"String"},"countries":{"type":"Country"},"__typename":{"type":"String"}}},"ID":{"__isAUsedScalarType":true},"Country":{"fields":{"code":{"type":"ID"},"name":{"type":"String"},"native":{"type":"String"},"phone":{"type":"String"},"continent":{"type":"Continent"},"capital":{"type":"String"},"currency":{"type":"String"},"languages":{"type":"Language"},"emoji":{"type":"String"},"emojiU":{"type":"String"},"states":{"type":"State"},"__typename":{"type":"String"}}},"Language":{"fields":{"code":{"type":"ID"},"name":{"type":"String"},"native":{"type":"String"},"rtl":{"type":"Boolean"},"__typename":{"type":"String"}}},"Boolean":{"__isAUsedScalarType":true},"State":{"fields":{"code":{"type":"String"},"name":{"type":"String"},"country":{"type":"Country"},"__typename":{"type":"String"}}},"CountryFilterInput":{"fields":{"code":{"type":"StringQueryOperatorInput"},"currency":{"type":"StringQueryOperatorInput"},"continent":{"type":"StringQueryOperatorInput"},"__typename":{"type":"String"}}},"LanguageFilterInput":{"fields":{"code":{"type":"StringQueryOperatorInput"},"__typename":{"type":"String"}}},"CacheControlScope":{"__isAUsedScalarType":true},"Upload":{"__isAUsedScalarType":true},"Int":{"__isAUsedScalarType":true}}